flask_transit.py
Flask_Transit-0.1.0_pre.dist-info/DESCRIPTION.rst
Flask_Transit-0.1.0_pre.dist-info/METADATA
Flask_Transit-0.1.0_pre.dist-info/metadata.json
Flask_Transit-0.1.0_pre.dist-info/RECORD
Flask_Transit-0.1.0_pre.dist-info/top_level.txt
Flask_Transit-0.1.0_pre.dist-info/WHEEL
