Metadata-Version: 2.0
Name: Flask-Transit
Version: 0.1.0-pre
Summary: A flask extension for working with transit data.
Home-page: http://github.com/obmarg/flask-transit
Author: Graeme Coupar
Author-email: grambo@grambo.me.uk
License: BSD
Platform: any
Classifier: Environment :: Web Environment
Classifier: Intended Audience :: Developers
Classifier: License :: OSI Approved :: BSD License
Classifier: Operating System :: OS Independent
Classifier: Programming Language :: Python
Classifier: Programming Language :: Python :: 2.7
Classifier: Development Status :: 4 - Beta
Classifier: Topic :: Internet :: WWW/HTTP :: Dynamic Content
Classifier: Topic :: Software Development :: Libraries :: Python Modules
Requires-Dist: Flask
Requires-Dist: transit-python
